pygmenus/__init__.py
pygmenus/button.py
pygmenus/image_interface.py
pygmenus/right_click_popup.py
pygmenus/slider.py
pygmenus/textbox.py
pygmenus-0.0.1.8.dist-info/METADATA
pygmenus-0.0.1.8.dist-info/WHEEL
pygmenus-0.0.1.8.dist-info/top_level.txt
pygmenus-0.0.1.8.dist-info/RECORD
