Metadata-Version: 2.1
Name: pygmenus
Version: 0.0.1.8
Summary: A simple menu system for Pygame.
Home-page: UNKNOWN
Author: @JoshuaParsonsCreativity
Author-email: your.email@example.com
License: UNKNOWN
Keywords: pygame,menu
Platform: UNKNOWN
